fi/Aggregates.py
fi/Aggregates.pyi
fi/CoveredWarrantData.py
fi/CoveredWarrantData.pyi
fi/DerivativeData.py
fi/DerivativeData.pyi
fi/FiinIndicator.py
fi/FiinIndicator.pyi
fi/FiinSession.py
fi/FiinSession.pyi
fi/SubscribeCoveredWarrantEvents.py
fi/SubscribeCoveredWarrantEvents.pyi
fi/SubscribeDerivativeEvents.py
fi/SubscribeDerivativeEvents.pyi
fi/SubscribeIndexEvents.py
fi/SubscribeIndexEvents.pyi
fi/SubscribeTickerEvents.py
fi/SubscribeTickerEvents.pyi
fi/SubscribeTickerUpdate.py
fi/SubscribeTickerUpdate.pyi
fi/TickerData.py
fi/TickerData.pyi
fi/UpdateData.py
fi/UpdateData.pyi
fi/__init__.py
fi/pyarmor_runtime_000000/pyarmor_runtime.pyd
fiiii/Aggregates.py
fiiii/Aggregates.pyi
fiiii/CoveredWarrantData.py
fiiii/CoveredWarrantData.pyi
fiiii/DerivativeData.py
fiiii/DerivativeData.pyi
fiiii/FiinIndicator.py
fiiii/FiinIndicator.pyi
fiiii/FiinSession.py
fiiii/FiinSession.pyi
fiiii/SubscribeCoveredWarrantEvents.py
fiiii/SubscribeCoveredWarrantEvents.pyi
fiiii/SubscribeDerivativeEvents.py
fiiii/SubscribeDerivativeEvents.pyi
fiiii/SubscribeIndexEvents.py
fiiii/SubscribeIndexEvents.pyi
fiiii/SubscribeTickerEvents.py
fiiii/SubscribeTickerEvents.pyi
fiiii/SubscribeTickerUpdate.py
fiiii/SubscribeTickerUpdate.pyi
fiiii/TickerData.py
fiiii/TickerData.pyi
fiiii/UpdateData.py
fiiii/UpdateData.pyi
fiiii/__init__.py
fiiii/pyarmor_runtime_000000/pyarmor_runtime.pyd
fiiii-0.3.dist-info/METADATA
fiiii-0.3.dist-info/WHEEL
fiiii-0.3.dist-info/top_level.txt
fiiii-0.3.dist-info/RECORD
